cloud_storage_clients/__init__.py
cloud_storage_clients/azure/__init__.py
cloud_storage_clients/azure/client.py
cloud_storage_clients/azure/factory.py
cloud_storage_clients/cache.py
cloud_storage_clients/client.py
cloud_storage_clients/connector.py
cloud_storage_clients/exceptions.py
cloud_storage_clients/gcs/__init__.py
cloud_storage_clients/gcs/client.py
cloud_storage_clients/gcs/factory.py
cloud_storage_clients/gcs/signer.py
cloud_storage_clients/pool.py
cloud_storage_clients/repositories/__init__.py
cloud_storage_clients/repositories/constant.py
cloud_storage_clients/repositories/credentials.py
cloud_storage_clients/repositories/env.py
cloud_storage_clients/repositories/vault.py
cloud_storage_clients/repositories/vault_adapter.py
cloud_storage_clients/responses.py
cloud_storage_clients/s3/__init__.py
cloud_storage_clients/s3/client.py
cloud_storage_clients/s3/factory.py
cloud_storage_clients-0.3.0.dist-info/LICENSE
cloud_storage_clients-0.3.0.dist-info/METADATA
cloud_storage_clients-0.3.0.dist-info/WHEEL
cloud_storage_clients-0.3.0.dist-info/RECORD
