Metadata-Version: 2.3
Name: cloud-storage-clients
Version: 0.3.0
Summary: Storage clients for different cloud providers
Author: picsellia
Author-email: pierre-nicolas@picsellia.com
Requires-Python: >=3.10
Classifier: Programming Language :: Python :: 3
Classifier: Programming Language :: Python :: 3.10
Classifier: Programming Language :: Python :: 3.11
Classifier: Programming Language :: Python :: 3.12
Classifier: Programming Language :: Python :: 3.13
Requires-Dist: azure-identity (>=1.15,<2)
Requires-Dist: azure-storage-blob (>=12.19.0,<13)
Requires-Dist: boto3 (>=1.33.1,<2)
Requires-Dist: google-cloud-storage (>=3,<4)
Requires-Dist: hvac (>=2,<3)
